LICENSE
MANIFEST.in
README.rst
setup.py
conf/org.gnome.pinboard.search.conf
conf/org.gnome.pinboard.search.gschema.xml
conf/org.gnome.pinboard.search.ini
conf/org.gnome.pinboard.search.service
data/popup.glade
gnome_shell_search_pinboard.egg-info/PKG-INFO
gnome_shell_search_pinboard.egg-info/SOURCES.txt
gnome_shell_search_pinboard.egg-info/dependency_links.txt
gnome_shell_search_pinboard.egg-info/entry_points.txt
gnome_shell_search_pinboard.egg-info/not-zip-safe
gnome_shell_search_pinboard.egg-info/requires.txt
gnome_shell_search_pinboard.egg-info/top_level.txt
gs_search_pinboard/__init__.py
gs_search_pinboard/daemon.py
gs_search_pinboard/pinboardutils.py
gs_search_pinboard/popup.py