Metadata-Version: 1.0
Name: gnome-shell-search-pinboard
Version: 1.0.0
Summary: A gnome shell search provider for your pinboard.in account
Home-page: http://github.com/ralphbean/gnome-shell-search-pinboard
Author: Ralph Bean
Author-email: rbean@redhat.com
License: GPLv3
Platform: UNKNOWN
